<?xml version="1.0" encoding="UTF-8"?>
<objects serializationModel="Studio.02.00.00">
	<object class="AudioFile" id="{2f0fa5e9-1734-425b-8106-9f3dfd95d42c}">
		<property name="assetPath">
			<value>Ambiance rue au loin.wav</value>
		</property>
		<property name="isStreaming">
			<value>true</value>
		</property>
		<property name="frequencyInKHz">
			<value>48</value>
		</property>
		<property name="channelCount">
			<value>1</value>
		</property>
		<property name="length">
			<value>54.296250000000001</value>
		</property>
		<relationship name="masterAssetFolder">
			<destination>{16ea86b1-db75-46f2-b94f-b98a88695656}</destination>
		</relationship>
	</object>
</objects>
