<?xml version="1.0" encoding="UTF-8"?>
<objects serializationModel="Studio.02.00.00">
	<object class="AudioFile" id="{41a53133-d7f6-4606-a3f2-1d1bb977a5a3}">
		<property name="assetPath">
			<value>Musique_DebutCombqt_Nanoprojet.wav</value>
		</property>
		<property name="isStreaming">
			<value>true</value>
		</property>
		<property name="frequencyInKHz">
			<value>44.0999985</value>
		</property>
		<property name="channelCount">
			<value>2</value>
		</property>
		<property name="length">
			<value>21.333333333333332</value>
		</property>
		<relationship name="masterAssetFolder">
			<destination>{16ea86b1-db75-46f2-b94f-b98a88695656}</destination>
		</relationship>
	</object>
</objects>
